README.rst
setup.py
pyspiderman.egg-info/PKG-INFO
pyspiderman.egg-info/SOURCES.txt
pyspiderman.egg-info/dependency_links.txt
pyspiderman.egg-info/top_level.txt
spiderman/__init__.py
spiderman/items.py
spiderman/middlewares.py
spiderman/pipelines.py
spiderman/settings.py
spiderman/spiders/__init__.py
spiderman/spiders/cbdioSpiders/__init__.py
spiderman/spiders/cbdioSpiders/cbdioSpider.py
spiderman/spiders/douban_movie/__init__.py
spiderman/spiders/douban_movie/doubanMovieSpider.py
spiderman/spiders/example_spiders/__init__.py
spiderman/spiders/example_spiders/example_spider.py
spiderman/spiders/netease_music/HotMusicSpider.py
spiderman/spiders/netease_music/__init__.py
spiderman/spiders/netease_music/workspace/__init__.py
spiderman/spiders/redisSpiders/RedisSpider.py
spiderman/spiders/redisSpiders/__init__.py
spiderman/utils/__init__.py
spiderman/utils/test.py
spiderman/utils/DB/MysqlPool.py
spiderman/utils/DB/OraclePool.py
spiderman/utils/DB/RedisPool.py
spiderman/utils/DB/__init__.1.py
spiderman/utils/DB/__init__.py
spiderman/utils/Exception/__init__.py
spiderman/utils/Middlewares/CustomStatsCollector.py
spiderman/utils/Middlewares/RandCookies.py
spiderman/utils/Middlewares/RandProxy.py
spiderman/utils/Middlewares/RandUserAgent.py
spiderman/utils/Middlewares/SeleniumMiddleware.py
spiderman/utils/Middlewares/__init__.py
spiderman/utils/Monitor/StatsMonitor.py
spiderman/utils/Monitor/__init__.py
spiderman/utils/Monitor/sendWarningMsg.py