Metadata-Version: 1.2
Name: pyspiderman
Version: 0.7a1
Summary: scrapy project integrated with useful utils,focus on programing your spider logic.
Home-page: https://github.com/vikky-lin/spiderman
Author: vikky
Author-email: 1309550760@qq.com
Maintainer: vikky
Maintainer-email: 1309550760@qq.com
License: Apache License 2.0
Platform: all
Classifier: Development Status :: 4 - Beta
Classifier: Operating System :: OS Independent
Classifier: Intended Audience :: Developers
Classifier: Programming Language :: Python
Classifier: Programming Language :: Python :: Implementation
Classifier: Programming Language :: Python :: 2
Classifier: Programming Language :: Python :: 2.7
Classifier: Programming Language :: Python :: 3
Classifier: Programming Language :: Python :: 3.4
Classifier: Programming Language :: Python :: 3.5
Classifier: Programming Language :: Python :: 3.6
Classifier: Topic :: Software Development :: Libraries
